AnswerAutomationService/__init__.py
AnswerAutomationService/__main__.py
AnswerAutomationService/const.py
AnswerAutomationService/service.py
pih_answ_auto-0.25.3.dist-info/METADATA
pih_answ_auto-0.25.3.dist-info/WHEEL
pih_answ_auto-0.25.3.dist-info/entry_points.txt
pih_answ_auto-0.25.3.dist-info/top_level.txt
pih_answ_auto-0.25.3.dist-info/RECORD
