Metadata-Version: 2.1
Name: pih-answ_auto
Version: 0.25.3
Summary: PIH Answer automation service package
Home-page: https://pacifichosp.com/
Author: Nikita Karachentsev
Author-email: it@pacifichosp.com
License: MIT
Requires-Dist: ipih
